grapherz/__init__.py
grapherz/core.py
grapherz/canvas/__init__.py
grapherz/canvas/core.py
grapherz/mermaid/__init__.py
grapherz/mermaid/core.py
grapherz/network/__init__.py
grapherz/network/core.py
grapherz-0.1.7.dist-info/METADATA
grapherz-0.1.7.dist-info/WHEEL
grapherz-0.1.7.dist-info/top_level.txt
grapherz-0.1.7.dist-info/RECORD
