Metadata-Version: 2.4
Name: grapherz
Version: 0.1.7
Summary: 负责提供graph之间的格式调度
Requires-Python: >=3.10
Requires-Dist: numpy>=2.2.4
Requires-Dist: pytest>=8.3.5
Requires-Dist: pytest-html>=4.1.1
Requires-Dist: python-box>=7.3.2
Requires-Dist: setuptools>=78.1.0
